pyimgy/__init__.py
pyimgy/core.py
pyimgy/image_crop.py
pyimgy/utils.py
pyimgy/optional/__init__.py
pyimgy/optional/fastai.py
pyimgy/optional/torch.py
pyimgy/optional/torch_utils.py
pyimgy/video/__init__.py
pyimgy/video/video_utils.py
pyimgy-0.1.0.dist-info/LICENSE
pyimgy-0.1.0.dist-info/METADATA
pyimgy-0.1.0.dist-info/WHEEL
pyimgy-0.1.0.dist-info/top_level.txt
pyimgy-0.1.0.dist-info/RECORD
